incept/__init__.py
incept/client.py
incept/exceptions.py
incept/models.py
tests/__init__.py
tests/conftest.py
tests/test_client.py
tests/test_models.py
incept_python_sdk-0.1.2.dist-info/METADATA
incept_python_sdk-0.1.2.dist-info/WHEEL
incept_python_sdk-0.1.2.dist-info/top_level.txt
incept_python_sdk-0.1.2.dist-info/RECORD
