Metadata-Version: 2.4
Name: incept-python-sdk
Version: 0.1.2
Summary: Python SDK for Incept Question Generation API
Home-page: https://github.com/incept/incept-python-sdk
Author: Incept
Author-email: Incept <support@inceptapi.com>
License: MIT
Project-URL: Homepage, https://github.com/incept/incept-python-sdk
Project-URL: Documentation, https://docs.inceptapi.com
Project-URL: Repository, https://github.com/incept/incept-python-sdk
Project-URL: Bug Tracker, https://github.com/incept/incept-python-sdk/issues
Classifier: Development Status :: 3 - Alpha
Classifier: Intended Audience :: Developers
Classifier: License :: OSI Approved :: MIT License
Classifier: Operating System :: OS Independent
Classifier: Programming Language :: Python :: 3
Classifier: Programming Language :: Python :: 3.7
Classifier: Programming Language :: Python :: 3.8
Classifier: Programming Language :: Python :: 3.9
Classifier: Programming Language :: Python :: 3.10
Classifier: Programming Language :: Python :: 3.11
Classifier: Programming Language :: Python :: 3.12
Requires-Python: >=3.7
Requires-Dist: requests>=2.25.0
Requires-Dist: pydantic>=1.8.0
Provides-Extra: dev
Requires-Dist: pytest>=6.0; extra == "dev"
Requires-Dist: pytest-cov>=2.0; extra == "dev"
Requires-Dist: requests-mock>=1.9.0; extra == "dev"
Requires-Dist: black>=21.0; extra == "dev"
Requires-Dist: flake8>=3.9; extra == "dev"
Requires-Dist: mypy>=0.910; extra == "dev"
Dynamic: author
Dynamic: home-page
Dynamic: requires-python
